echostream_node/__init__.py
echostream_node/asyncio/__init__.py
echostream_node/threading/__init__.py
echostream_node-0.4.6.dist-info/LICENSE
echostream_node-0.4.6.dist-info/METADATA
echostream_node-0.4.6.dist-info/WHEEL
echostream_node-0.4.6.dist-info/top_level.txt
echostream_node-0.4.6.dist-info/RECORD
