Metadata-Version: 2.2
Name: echostream-node
Version: 0.4.6
Summary: EchoStream library for implementing remote nodes
Author: EchoStream
Author-email: pypi@echo.stream
Requires-Python: >=3.12
License-File: LICENSE
Requires-Dist: aws-error-utils==2.7.0
Requires-Dist: awsserviceendpoints==0.0.2
Requires-Dist: boto3>=1.34.42
Requires-Dist: botocore>=1.34.42
Requires-Dist: dynamic-function-loader==0.0.3
Requires-Dist: echostream-botocore==0.1.0
Requires-Dist: gql[aiohttp,requests]==3.5.0
Requires-Dist: gql-appsync-cognito-authentication==0.0.1
Requires-Dist: httpx==0.28.1
Requires-Dist: httpx-auth==0.23.1
Requires-Dist: pycognito==2024.5.1
Requires-Dist: simplejson==3.19.3
